{"name":"Bbp-user-online-status","tagline":"A Wordpress plugin to show user online/offline status in bbpress topics and replies","body":"# BBP User Online Status\r\nA Wordpress plugin to show user online/offline statuses in bbpress topics and replies\r\n\r\nSimply adds an \"Online\" or \"Offline\" under the author information in [bbpress](https://bbpress.org/) topics and replies.\r\n\r\nParts of code adapted from Robin Wilson's [bbp profile information](https://wordpress.org/plugins/bbp-profile-information/), Raul Illana's [Awebsome! Online Registered Users Widget](https://wordpress.org/plugins/awebsome-online-registered-users-widget/), and from [onetrickpony](http://wordpress.stackexchange.com/questions/34429/how-to-check-if-a-user-not-current-user-is-logged-in) at stackoverflow.\r\n\r\nOnline\r\n![](https://github.com/abreksa4/bbp-user-online-status/blob/master/assets/screenshot-1.PNG?raw=true)\r\n\r\nOffline\r\n![](https://github.com/abreksa4/bbp-user-online-status/blob/master/assets/screenshot-2.PNG?raw=true)\r\n\r\nSettings\r\n![](https://github.com/abreksa4/bbp-user-online-status/blob/master/assets/screenshot-3.PNG?raw=true)\r\n","google":"","note":"Don't delete this file! It's used internally to help with page regeneration."}